kowaza/__init__.py
kowaza/_nbdev.py
kowaza/core.py
kowaza/jpinfo.py
kowaza/mli.py
kowaza-0.0.3.dist-info/LICENSE
kowaza-0.0.3.dist-info/METADATA
kowaza-0.0.3.dist-info/WHEEL
kowaza-0.0.3.dist-info/entry_points.txt
kowaza-0.0.3.dist-info/top_level.txt
kowaza-0.0.3.dist-info/RECORD
